{
    "countries": [
      {
        "id": 1,
        "name": "Australia",
        "cities": [
          {
            "name": "Sydney, Australia",
            "imageUrl": "https://media.tatler.com/photos/6141d37b9ce9874a3e40107d/16:9/w_1280,c_limit/social_crop_sydney_opera_house_gettyimages-869714270.jpg",
            "description": "A vibrant city known for its iconic landmarks like the Sydney Opera House and Sydney Harbour Bridge."
          },
          {
            "name": "Melbourne, Australia",
            "imageUrl": "https://www.aeccglobal.com/images/easyblog_articles/112/8-Optimized-shutterstock_274387127.jpg",
            "description": "A cultural hub famous for its art, food, and diverse neighborhoods."
          }
        ]
      },
      {
        "id": 2,
        "name": "Japan",
        "cities": [
          {
            "name": "Tokyo, Japan",
            "imageUrl": "https://a.loveholidays.com/media-library/~production/6d7b5475d338ee30647c4b88d27fea204429081c-3840x1408.jpg?auto=avif%2Cwebp&quality=80&dpr=1.5&optimize=high&fit=crop&width=1280&height=380",
            "description": "A bustling metropolis blending tradition and modernity, famous for its cherry blossoms and rich culture."
          },
          {
            "name": "Kyoto, Japan",
            "imageUrl": "https://www.travelcaffeine.com/wp-content/uploads/2020/03/hirano-shrine-cherry-blossom-hanami-sakura-season-kyoto-japan-sunburst-torii.jpg",
            "description": "Known for its historic temples, gardens, and traditional tea houses."
          }
        ]
      },
      {
        "id": 3,
        "name": "Brazil",
        "cities": [
          {
            "name": "Rio de Janeiro, Brazil",
            "imageUrl": "https://cdn.mos.cms.futurecdn.net/dxiLtztp2NSCZMRY3SBZne.jpg",
            "description": "A lively city known for its stunning beaches, vibrant carnival celebrations, and iconic landmarks."
          },
          {
            "name": "São Paulo, Brazil",
            "imageUrl": "https://encrypted-tbn0.gstatic.com/images?q=tbn:ANd9GcROVDYFmugaqqZKf-T4cVJESHtyF_xoo2aRIqo0EQtJMA&s",
            "description": "The financial hub with diverse culture, arts, and a vibrant nightlife."
          }
        ]
      }
    ],
    "temples": [
      {
        "id": 1,
        "name": "Angkor Wat, Cambodia",
        "imageUrl": "https://content.api.news/v3/images/bin/debbac6348b6555b9f42de018d2a3acd",
        "description": "A UNESCO World Heritage site and the largest religious monument in the world."
      },
      {
        "id": 2,
        "name": "Taj Mahal, India",
        "imageUrl": "https://media.cnn.com/api/v1/images/stellar/prod/171017153620-the-taj-mahal-general-view.jpg?q=x_0,y_156,h_1688,w_3000,c_crop/h_833,w_1480",
        "description": "An iconic symbol of love and a masterpiece of Mughal architecture."
      }
    ],
    "beaches": [
      {
        "id": 1,
        "name": "Bora Bora, French Polynesia",
        "imageUrl": "https://encrypted-tbn0.gstatic.com/images?q=tbn:ANd9GcSrlWdNxxiV6rL102BdMscFD7CyMb55GsUzDDQ0LNLJcg&s",
        "description": "An island known for its stunning turquoise waters and luxurious overwater bungalows."
      },
      {
        "id": 2,
        "name": "Copacabana Beach, Brazil",
        "imageUrl": "https://encrypted-tbn0.gstatic.com/images?q=tbn:ANd9GcQLQevRmIszL4wVR_1UJUJQMNrDz07e123dX6LSdByfXQ&s",
        "description": "A famous beach in Rio de Janeiro, Brazil, with a vibrant atmosphere and scenic views."
      }
    ]
  }
  